mariqt_widgets/__init__.py
mariqt_widgets/ifdo_create.py
mariqt_widgets/ifdo_excel.py
mariqt_widgets/notebook_widgets.py
mariqt_widgets/icons/checkbox-circle-line_gray.png
mariqt_widgets/icons/checkbox-circle-line_green.png
mariqt_widgets/icons/error-warning-line_gray.png
mariqt_widgets/icons/error-warning-line_orange.png
mariqt_widgets/icons/error-warning-line_red.png
mariqt_widgets-0.4.2.dist-info/AUTHORS.md
mariqt_widgets-0.4.2.dist-info/LICENSE
mariqt_widgets-0.4.2.dist-info/METADATA
mariqt_widgets-0.4.2.dist-info/WHEEL
mariqt_widgets-0.4.2.dist-info/top_level.txt
mariqt_widgets-0.4.2.dist-info/RECORD
